django_ticket-3.1.3.dist-info/licenses/LICENSE
ticket/__init__.py
ticket/admin.py
ticket/apps.py
ticket/context_processors.py
ticket/models.py
ticket/serializers.py
ticket/signals.py
ticket/urls.py
ticket/views.py
django_ticket-3.1.3.dist-info/METADATA
django_ticket-3.1.3.dist-info/WHEEL
django_ticket-3.1.3.dist-info/top_level.txt
django_ticket-3.1.3.dist-info/RECORD
