Metadata-Version: 2.4
Name: django-ticket
Version: 3.1.3
Summary: A ticket application for Django projects
Home-page: https://github.com/HosseinSayyedMousavi/django-ticket
Author: Abbas Ebadian
Author-email: AbbasEbadiann@gmail.com
Maintainer: Hossein Sayyedmousavi
Maintainer-email: Hossein.Sayyedmousavi@gmail.com
Keywords: django,database,ticket
Classifier: Development Status :: 4 - Beta
Classifier: Environment :: Web Environment
Classifier: Environment :: Console
Classifier: Framework :: Django :: 2.2
Classifier: Framework :: Django :: 3.2
Classifier: Framework :: Django :: 4.2
Classifier: Intended Audience :: Developers
Classifier: Intended Audience :: System Administrators
Classifier: License :: OSI Approved :: BSD License
Classifier: Natural Language :: English
Classifier: Operating System :: OS Independent
Classifier: Programming Language :: Python
Classifier: Programming Language :: Python :: 3.6
Classifier: Programming Language :: Python :: 3.7
Classifier: Programming Language :: Python :: 3.8
Classifier: Programming Language :: Python :: 3.9
Classifier: Programming Language :: Python :: 3.10
Classifier: Topic :: Database
Classifier: Topic :: System :: Archiving
Classifier: Topic :: System :: Archiving :: Compression
License-File: LICENSE
Requires-Dist: django
Requires-Dist: djangorestframework
Requires-Dist: drf-spectacular
Dynamic: author
Dynamic: author-email
Dynamic: classifier
Dynamic: description
Dynamic: description-content-type
Dynamic: home-page
Dynamic: keywords
Dynamic: license-file
Dynamic: maintainer
Dynamic: maintainer-email
Dynamic: requires-dist
Dynamic: summary
